{"name": "Bank 1", "pedalboards": [{"name": "Pedalboard 1", "connections": [{"type": "audio", "input": {"index": 0, "symbol": "in_l", "effect": 0}, "output": {"symbol": "capture_1", "index": 0}}, {"type": "audio", "input": {"index": 0, "symbol": "in_l", "effect": 1}, "output": {"index": 2, "symbol": "out_l", "effect": 0}}, {"type": "audio", "input": {"symbol": "playback_1", "index": 0}, "output": {"index": 2, "symbol": "out_l", "effect": 1}}, {"type": "audio", "input": {"symbol": "playback_2", "index": 1}, "output": {"index": 2, "symbol": "out_l", "effect": 1}}], "data": {}, "effects": [{"active": true, "plugin": "http://calf.sourceforge.net/plugins/Flanger", "technology": "lv2", "version": "0.60", "params": [{"value": 0.10000000149011612, "symbol": "min_delay", "index": 4}, {"value": 1.0, "symbol": "mod_depth", "index": 5}, {"value": 0.20000000298023224, "symbol": "mod_rate", "index": 6}, {"value": 0.8999999761581421, "symbol": "feedback", "index": 7}, {"value": 90.0, "symbol": "stereo", "index": 8}, {"value": 0.0, "symbol": "reset", "index": 9}, {"value": 1.0, "symbol": "amount", "index": 10}, {"value": 1.0, "symbol": "dry", "index": 11}]}, {"active": true, "plugin": "http://calf.sourceforge.net/plugins/Reverb", "technology": "lv2", "version": "0.0", "params": [{"value": 1.5, "symbol": "decay_time", "index": 7}, {"value": 5000.0, "symbol": "hf_damp", "index": 8}, {"value": 2, "symbol": "room_size", "index": 9}, {"value": 0.5, "symbol": "diffusion", "index": 10}, {"value": 0.25, "symbol": "amount", "index": 11}, {"value": 1.0, "symbol": "dry", "index": 12}, {"value": 0.0, "symbol": "predelay", "index": 13}, {"value": 300.0, "symbol": "bass_cut", "index": 14}, {"value": 5000.0, "symbol": "treble_cut", "index": 15}]}]}, {"name": "Bypass", "connections": [{"type": "audio", "input": {"symbol": "playback_1", "index": 0}, "output": {"symbol": "capture_1", "index": 0}}], "data": {}, "effects": []}], "index": 0}